async_upnp_client/__init__.py
async_upnp_client/advertisement.py
async_upnp_client/aiohttp.py
async_upnp_client/cli.py
async_upnp_client/client.py
async_upnp_client/client_factory.py
async_upnp_client/const.py
async_upnp_client/description_cache.py
async_upnp_client/device_updater.py
async_upnp_client/event_handler.py
async_upnp_client/exceptions.py
async_upnp_client/py.typed
async_upnp_client/search.py
async_upnp_client/server.py
async_upnp_client/ssdp.py
async_upnp_client/ssdp_listener.py
async_upnp_client/utils.py
async_upnp_client/profiles/__init__.py
async_upnp_client/profiles/dlna.py
async_upnp_client/profiles/igd.py
async_upnp_client/profiles/printer.py
async_upnp_client/profiles/profile.py
async_upnp_client-0.46.1.dist-info/licenses/LICENSE.txt
async_upnp_client-0.46.1.dist-info/METADATA
async_upnp_client-0.46.1.dist-info/WHEEL
async_upnp_client-0.46.1.dist-info/entry_points.txt
async_upnp_client-0.46.1.dist-info/top_level.txt
async_upnp_client-0.46.1.dist-info/RECORD
