Metadata-Version: 2.4
Name: async_upnp_client
Version: 0.46.1
Summary: Async UPnP Client
Author-email: Steven Looman <steven.looman@gmail.com>
License-Expression: Apache-2.0
Project-URL: GitHub: repo, https://github.com/StevenLooman/async_upnp_client
Keywords: ssdp,Simple Service Discovery Protocol,upnp,Universal Plug and Play
Classifier: Development Status :: 5 - Production/Stable
Classifier: Intended Audience :: Developers
Classifier: Framework :: AsyncIO
Classifier: Operating System :: POSIX
Classifier: Operating System :: MacOS :: MacOS X
Classifier: Operating System :: Microsoft :: Windows
Classifier: Programming Language :: Python :: 3.10
Classifier: Programming Language :: Python :: 3.11
Classifier: Programming Language :: Python :: 3.12
Classifier: Programming Language :: Python :: 3.13
Classifier: Programming Language :: Python :: 3.14
Requires-Python: >=3.10
License-File: LICENSE.txt
Requires-Dist: aiohttp<4.0,>3.9.0
Requires-Dist: defusedxml>=0.6.0
Requires-Dist: python-didl-lite~=1.4.0
Requires-Dist: voluptuous>=0.15.2
Dynamic: license-file
